multidirmap/__init__.py
multidirmap/_multidirmaprow.py
multidirmap/_read_only_dict.py
multidirmap/_util.py
multidirmap/multidirmap.py
multidirmap-0.3.0.dist-info/AUTHORS.rst
multidirmap-0.3.0.dist-info/LICENSE
multidirmap-0.3.0.dist-info/METADATA
multidirmap-0.3.0.dist-info/WHEEL
multidirmap-0.3.0.dist-info/top_level.txt
multidirmap-0.3.0.dist-info/RECORD
